LICENSE
README.md
setup.py
similarities/__init__.py
similarities/bert_similarity.py
similarities/cli.py
similarities/clip_module.py
similarities/clip_similarity.py
similarities/data_loader.py
similarities/ensemble_similarity.py
similarities/evaluation.py
similarities/faiss_bert_similarity.py
similarities/faiss_clip_similarity.py
similarities/fast_bert_similarity.py
similarities/image_similarity.py
similarities/literal_similarity.py
similarities/similarity.py
similarities/version.py
similarities.egg-info/PKG-INFO
similarities.egg-info/SOURCES.txt
similarities.egg-info/dependency_links.txt
similarities.egg-info/entry_points.txt
similarities.egg-info/not-zip-safe
similarities.egg-info/requires.txt
similarities.egg-info/top_level.txt
similarities/data/cilin.txt
similarities/data/hownet.txt
similarities/data/stopwords.txt
similarities/utils/__init__.py
similarities/utils/distance.py
similarities/utils/get_file.py
similarities/utils/image_util.py
similarities/utils/imagehash.py
similarities/utils/rank_bm25.py
similarities/utils/tfidf.py
similarities/utils/util.py
tests/test_fastsim.py
tests/test_image_qps.py
tests/test_imagesim.py
tests/test_literalsim.py
tests/test_sim_score.py
tests/test_text_qps.py