Metadata-Version: 2.1
Name: similarities
Version: 1.2.1
Summary: Similarities is a toolkit for compute similarity scores between texts, performing text searches.
Home-page: https://github.com/shibing624/similarities
Author: XuMing
Author-email: xuming624@qq.com
License: Apache License 2.0
Keywords: similarities,Chinese Text Similarity Calculation Tool,similarity,word2vec
Classifier: Development Status :: 5 - Production/Stable
Classifier: Intended Audience :: Developers
Classifier: Intended Audience :: Education
Classifier: Intended Audience :: Science/Research
Classifier: License :: OSI Approved :: Apache Software License
Classifier: Operating System :: OS Independent
Classifier: Programming Language :: Python :: 3
Classifier: Topic :: Scientific/Engineering :: Artificial Intelligence
Requires-Python: >=3.6.0
License-File: LICENSE
Requires-Dist: text2vec>=1.2.9
Requires-Dist: jieba>=0.39
Requires-Dist: loguru
Requires-Dist: Pillow
Requires-Dist: fire
Requires-Dist: autofaiss
Requires-Dist: transformers
